clarity_sdk/NameCleaning.py
clarity_sdk/StringFunctions.py
clarity_sdk/__init__.py
clarity_sdk/version.py
Clarity_SDK-1.0.9.dist-info/LICENSE
Clarity_SDK-1.0.9.dist-info/METADATA
Clarity_SDK-1.0.9.dist-info/WHEEL
Clarity_SDK-1.0.9.dist-info/top_level.txt
Clarity_SDK-1.0.9.dist-info/RECORD
