Metadata-Version: 2.1
Name: Clarity-SDK
Version: 1.0.9
Summary: Python SDK for the Clarity API
Home-page: https://test.pypi.org/legacy/
Author: Intuli
Author-email: intuli.developer@gmail.com
License: UNKNOWN
Platform: UNKNOWN
Classifier: Programming Language :: Python :: 3
Classifier: License :: OSI Approved :: MIT License
Classifier: Operating System :: OS Independent
